{
  "barrio": "Flores",
  "mes": "noviembre",
  "año": 2025,
  "eventos": [
    {
      "nombre": "La Noche de los Museos",
      "fecha": "2025-11-08",
      "tipo": "Cultural",
      "lugar": "Museo Barrio de Flores",
      "direccion": "Ramón Falcón 2207, Flores, Buenos Aires",
      "precio": "Gratuito",
      "hora": "19:00 a 02:00",
      "descripcion": "Más de 300 espacios culturales abren gratis. En Flores: Museo Barrio de Flores, Estación de Bomberos, Escuelas Museo, 921 Casa Cultural, Espacio Cultural Adán Buenosayres, etc.",
      "url": "",
      "categoria": "cultural"
    },
    {
      "nombre": "Show de Rock - Nueva Ética",
      "fecha": "2025-11-09",
      "tipo": "Musica",
      "lugar": "El Teatro Flores",
      "direccion": "Av. Rivadavia 7806, Flores, Buenos Aires",
      "precio": "",
      "hora": "",
      "descripcion": "Espectáculo de rock.",
      "url": "",
      "categoria": "concierto"
    },
    {
      "nombre": "Show de Rock - ASSPERA",
      "fecha": "2025-11-15",
      "tipo": "Musica",
      "lugar": "El Teatro Flores",
      "direccion": "Av. Rivadavia 7806, Flores, Buenos Aires",
      "precio": "",
      "hora": "",
      "descripcion": "Espectáculo de rock y metal.",
      "url": "",
      "categoria": "concierto"
    },
    {
      "nombre": "Show de Rock - NVLO",
      "fecha": "2025-11-16",
      "tipo": "Musica",
      "lugar": "El Teatro Flores",
      "direccion": "Av. Rivadavia 7806, Flores, Buenos Aires",
      "precio": "",
      "hora": "",
      "descripcion": "Espectáculo de rock y metal.",
      "url": "",
      "categoria": "concierto"
    },
    {
      "nombre": "Feria del Libro Punky y Derivados",
      "fecha": "2025-11-15",
      "tipo": "Feria",
      "lugar": "Casona de Flores",
      "direccion": "Morón 2453, Flores, Buenos Aires",
      "precio": "",
      "hora": "",
      "descripcion": "Feria de fanzines, publicaciones y libros alternativos.",
      "url": "",
      "categoria": "feria"
    },
    {
      "nombre": "Feria del Libro Punky y Derivados",
      "fecha": "2025-11-16",
      "tipo": "Feria",
      "lugar": "Casona de Flores",
      "direccion": "Morón 2453, Flores, Buenos Aires",
      "precio": "",
      "hora": "",
      "descripcion": "Feria de fanzines, publicaciones y libros alternativos.",
      "url": "",
      "categoria": "feria"
    },
    {
      "nombre": "Show de Rock - Científicos del Palo",
      "fecha": "2025-11-21",
      "tipo": "Musica",
      "lugar": "El Teatro Flores",
      "direccion": "Av. Rivadavia 7806, Flores, Buenos Aires",
      "precio": "",
      "hora": "",
      "descripcion": "Espectáculo de rock.",
      "url": "",
      "categoria": "concierto"
    },
    {
      "nombre": "Show de Rock - Avantasia",
      "fecha": "2025-11-27",
      "tipo": "Musica",
      "lugar": "El Teatro Flores",
      "direccion": "Av. Rivadavia 7806, Flores, Buenos Aires",
      "precio": "",
      "hora": "",
      "descripcion": "Espectáculo de rock y metal.",
      "url": "",
      "categoria": "concierto"
    },
    {
      "nombre": "Buenos Aires Rojo Sangre (Festival de Cine)",
      "fecha": "2025-11-20",
      "tipo": "Cine",
      "lugar": "Sedes por confirmar en CABA",
      "direccion": "CABA, Buenos Aires",
      "precio": "",
      "hora": "",
      "descripcion": "Festival internacional de cine de terror, fantástico y bizarro. Del 20 al 30 de Nov.",
      "url": "",
      "categoria": "festival"
    },
    {
      "nombre": "Noche de los Templos",
      "fecha": "2025-11-29",
      "tipo": "Cultural",
      "lugar": "Varios templos de distintos cultos en CABA",
      "direccion": "CABA, Buenos Aires",
      "precio": "Gratuito",
      "hora": "",
      "descripcion": "Recorridos y actividades especiales para conocer la diversidad religiosa de la Ciudad.",
      "url": "",
      "categoria": "cultural"
    }
  ],
  "lugares_interes": [
    {
      "nombre": "Museo Barrio de Flores",
      "direccion": "Ramón Falcón 2207, Flores, Buenos Aires",
      "tipo": "Museo",
      "descripcion": "Museo del barrio que participa en La Noche de los Museos.",
      "horario": "",
      "precio": ""
    },
    {
      "nombre": "Estación VII Flores - Bomberos de la Ciudad",
      "direccion": "Coronel Ramón L. Falcón 2255, Flores, Buenos Aires",
      "tipo": "Museo",
      "descripcion": "Estación de bomberos que participa en La Noche de los Museos.",
      "horario": "",
      "precio": ""
    },
    {
      "nombre": "Escuela N° 8 Cnel. Ing. Pedro Antonio Cerviño",
      "direccion": "Varela 358, Flores, Buenos Aires",
      "tipo": "Escuela Museo",
      "descripcion": "Escuela museo que participa en La Noche de los Museos.",
      "horario": "",
      "precio": ""
    },
    {
      "nombre": "Espacio Cultural Adán Buenosayres",
      "direccion": "Flores, Buenos Aires",
      "tipo": "Centro Cultural",
      "descripcion": "Centro cultural barrial con agenda semanal.",
      "horario": "",
      "precio": ""
    },
    {
      "nombre": "El Teatro Flores",
      "direccion": "Av. Rivadavia 7806, Flores, Buenos Aires",
      "tipo": "Teatro",
      "descripcion": "Teatro con espectáculos de rock y metal.",
      "horario": "",
      "precio": ""
    },
    {
      "nombre": "Casona de Flores",
      "direccion": "Morón 2453, Flores, Buenos Aires",
      "tipo": "Centro Cultural",
      "descripcion": "Espacio cultural que alberga ferias y eventos.",
      "horario": "",
      "precio": ""
    }
  ]
}
